trio_ftx/__init__.py
trio_ftx/client.py
trio_ftx/streams.py
trio_ftx-0.1.6.dist-info/LICENSE
trio_ftx-0.1.6.dist-info/WHEEL
trio_ftx-0.1.6.dist-info/METADATA
trio_ftx-0.1.6.dist-info/RECORD
