Metadata-Version: 2.1
Name: trio-ftx
Version: 0.1.6
Summary: Trio powered FTX async python client
License: BSD-3-Clause
Author: Shu Wang
Author-email: halfelf.ronin@gmail.com
Requires-Python: >=3.9,<4.0
Classifier: License :: OSI Approved :: BSD License
Classifier: Programming Language :: Python :: 3
Classifier: Programming Language :: Python :: 3.10
Classifier: Programming Language :: Python :: 3.9
Requires-Dist: ciso8601 (>=2.2.0,<3.0.0)
Requires-Dist: httpx (>0.20.0)
Requires-Dist: trio (>=0.20.0)
Requires-Dist: trio-websocket (>=0.9.2,<0.10.0)
